loomx/__init__.py
loomx/cli.py
loomx/config.py
loomx/formatter.py
loomx/graph.py
loomx/parser.py
loomx/processor.py
loomx/scanner.py
loomx-0.1.1.dist-info/METADATA
loomx-0.1.1.dist-info/WHEEL
loomx-0.1.1.dist-info/entry_points.txt
loomx-0.1.1.dist-info/licenses/LICENSE
loomx-0.1.1.dist-info/RECORD
