Metadata-Version: 2.4
Name: loomx
Version: 0.1.1
Summary: A CLI tool that adds reference and backlink metadata to markdown documentation files
Project-URL: Homepage, https://github.com/pawsong/loomx-py
Project-URL: Repository, https://github.com/pawsong/loomx-py
Project-URL: Issues, https://github.com/pawsong/loomx-py/issues
Author-email: Giff Song <giff.song@gmail.com>
License: MIT
License-File: LICENSE
Keywords: cli,developer-tools,documentation,links,markdown
Classifier: Development Status :: 4 - Beta
Classifier: Intended Audience :: Developers
Classifier: License :: OSI Approved :: MIT License
Classifier: Programming Language :: Python :: 3
Classifier: Programming Language :: Python :: 3.9
Classifier: Programming Language :: Python :: 3.10
Classifier: Programming Language :: Python :: 3.11
Classifier: Programming Language :: Python :: 3.12
Classifier: Programming Language :: Python :: 3.13
Classifier: Topic :: Documentation
Classifier: Topic :: Software Development :: Documentation
Classifier: Topic :: Text Processing :: Markup :: Markdown
Requires-Python: >=3.9
Requires-Dist: click>=8.1.0
Requires-Dist: mistune>=3.0.0
Requires-Dist: pathspec>=0.11.0
Requires-Dist: pyyaml>=6.0
Requires-Dist: tomli>=2.0.0; python_version < '3.11'
